CHANGELOG.rst
LICENSE
MANIFEST.in
README.rst
setup.py
django_mathfield.egg-info/PKG-INFO
django_mathfield.egg-info/SOURCES.txt
django_mathfield.egg-info/dependency_links.txt
django_mathfield.egg-info/top_level.txt
mathfield/__init__.py
mathfield/api.py
mathfield/generate_html.js
mathfield/models.py
mathfield/widgets.py
mathfield/static/mathfield/css/katex.min.css
mathfield/static/mathfield/css/mathfield.css
mathfield/static/mathfield/css/fonts/KaTeX_AMS-Regular.eot
mathfield/static/mathfield/css/fonts/KaTeX_AMS-Regular.ttf
mathfield/static/mathfield/css/fonts/KaTeX_AMS-Regular.woff
mathfield/static/mathfield/css/fonts/KaTeX_Main-Bold.eot
mathfield/static/mathfield/css/fonts/KaTeX_Main-Bold.ttf
mathfield/static/mathfield/css/fonts/KaTeX_Main-Bold.woff
mathfield/static/mathfield/css/fonts/KaTeX_Main-Italic.eot
mathfield/static/mathfield/css/fonts/KaTeX_Main-Italic.ttf
mathfield/static/mathfield/css/fonts/KaTeX_Main-Italic.woff
mathfield/static/mathfield/css/fonts/KaTeX_Main-Regular.eot
mathfield/static/mathfield/css/fonts/KaTeX_Main-Regular.ttf
mathfield/static/mathfield/css/fonts/KaTeX_Main-Regular.woff
mathfield/static/mathfield/css/fonts/KaTeX_Math-BoldItalic.eot
mathfield/static/mathfield/css/fonts/KaTeX_Math-BoldItalic.ttf
mathfield/static/mathfield/css/fonts/KaTeX_Math-BoldItalic.woff
mathfield/static/mathfield/css/fonts/KaTeX_Math-Italic.eot
mathfield/static/mathfield/css/fonts/KaTeX_Math-Italic.ttf
mathfield/static/mathfield/css/fonts/KaTeX_Math-Italic.woff
mathfield/static/mathfield/css/fonts/KaTeX_Math-Regular.eot
mathfield/static/mathfield/css/fonts/KaTeX_Math-Regular.ttf
mathfield/static/mathfield/css/fonts/KaTeX_Math-Regular.woff
mathfield/static/mathfield/css/fonts/KaTeX_Size1-Regular.eot
mathfield/static/mathfield/css/fonts/KaTeX_Size1-Regular.ttf
mathfield/static/mathfield/css/fonts/KaTeX_Size1-Regular.woff
mathfield/static/mathfield/css/fonts/KaTeX_Size2-Regular.eot
mathfield/static/mathfield/css/fonts/KaTeX_Size2-Regular.ttf
mathfield/static/mathfield/css/fonts/KaTeX_Size2-Regular.woff
mathfield/static/mathfield/css/fonts/KaTeX_Size3-Regular.eot
mathfield/static/mathfield/css/fonts/KaTeX_Size3-Regular.ttf
