Metadata-Version: 1.1
Name: django-mathfield
Version: 0.1.0
Summary: A Django model field for writing and displaying LaTeX
Home-page: https://github.com/jongoodnow/django-mathfield
Author: Jonathan Goodnow
Author-email: jon@goodnow.io
License: BSD
Keywords: django,math,latex,katex
Platform: UNKNOWN
Classifier: Development Status :: 3 - Alpha
Classifier: Intended Audience :: Developers
Classifier: License :: OSI Approved :: BSD License
Classifier: Natural Language :: English
Classifier: Operating System :: OS Independent
Classifier: Programming Language :: Python :: 2.7
Classifier: Environment :: Web Environment
Classifier: Framework :: Django
Classifier: Topic :: Utilities
